odoo/addons/project_task_hide_add_property/README.rst
odoo/addons/project_task_hide_add_property/__init__.py
odoo/addons/project_task_hide_add_property/__manifest__.py
odoo/addons/project_task_hide_add_property/readme/CONTRIBUTORS.rst
odoo/addons/project_task_hide_add_property/readme/DESCRIPTION.rst
odoo/addons/project_task_hide_add_property/static/description/icon.png
odoo/addons/project_task_hide_add_property/static/description/index.html
odoo/addons/project_task_hide_add_property/views/project_task_views.xml
odoo_addon_project_task_hide_add_property-16.0.1.0.0.1.dist-info/METADATA
odoo_addon_project_task_hide_add_property-16.0.1.0.0.1.dist-info/WHEEL
odoo_addon_project_task_hide_add_property-16.0.1.0.0.1.dist-info/top_level.txt
odoo_addon_project_task_hide_add_property-16.0.1.0.0.1.dist-info/RECORD
